glyconformer/__init__.py
glyconformer/lib.py
GlyCONFORMER-1.1.3.dist-info/LICENSE
GlyCONFORMER-1.1.3.dist-info/METADATA
GlyCONFORMER-1.1.3.dist-info/WHEEL
GlyCONFORMER-1.1.3.dist-info/top_level.txt
GlyCONFORMER-1.1.3.dist-info/RECORD
