Metadata-Version: 2.1
Name: GlyCONFORMER
Version: 1.1.3
Summary: GlyCONFORMERS is a Python package that assigns conformer strings to N-glycan conformers, based on their torsion angle values.
Author-email: Isabell Grothaus <grothaus@uni-bremen.de>
License: GPL-3.0 license
Project-URL: Homepage, https://github.com/IsabellGrothaus/GlyCONFORMER
Keywords: glycan,conformer,classification,sugar,carbohydrates
Classifier: Development Status :: 3 - Alpha
Classifier: Intended Audience :: Education
Classifier: Programming Language :: Python :: 3
Requires-Python: >=3.0
License-File: LICENSE
Requires-Dist: numpy ==1.26.4
Requires-Dist: matplotlib
Requires-Dist: pandas <=1.3.5
Requires-Dist: plumed
Requires-Dist: scipy
Requires-Dist: scikit-learn
Requires-Dist: wpca
